{
  "id" : "irxn6209",
  "equation" : null,
  "name" : null,
  "otherNames" : [ ],
  "alias" : null,
  "references" : [ {
    "source" : "LigandReaction",
    "entry" : "R01857"
  }, {
    "source" : "BiGGReaction",
    "entry" : "NDPK5m"
  }, {
    "source" : "BiGGReaction",
    "entry" : "ATDGDm"
  }, {
    "source" : "BiGGReaction",
    "entry" : "NDPK5"
  }, {
    "source" : "MetaCyc",
    "entry" : "META:DGDPKIN-RXN"
  }, {
    "source" : "BiGGReaction",
    "entry" : "NDPK5n"
  } ],
  "gibbs" : null,
  "metacycDirection" : null
}
